{"The May Fair Hotel": "United Kingdom", "Mercure London Bloomsbury Hotel": "United Kingdom", "Legend Saint Germain by Elegancia": "France", "Mercure Paris 19 Philharmonie La Villette": "France", "Golden Tulip Amsterdam West": "Nederland", "Novotel Milano Linate Aeroporto": "Italia", "Holiday Inn London Kensington Forum": "United Kingdom", "Mercure Josefshof Wien": "\u00d6sterreich", "The Gore Hotel Starhotels Collezione": "United Kingdom", "Hilton London Kensington Hotel": "United Kingdom", "Hotel Indigo London Kensington": "United Kingdom", "Number Sixteen": "United Kingdom", "Catalonia Park Putxet": "Espanya", "Ayre Hotel Caspe": "Espanya", "Crowne Plaza London Kings Cross": "United Kingdom", "Holiday Inn London Kensington": "United Kingdom", "New Linden Hotel": "United Kingdom", "Silken Ramblas": "Espanya", "Mondrian London": "United Kingdom", "Clayton Crown Hotel London": "United Kingdom", "Holiday Inn London Stratford City": "United Kingdom", "Park Plaza County Hall London": "United Kingdom", "H tel Arvor Saint Georges": "France", "The Ring Vienna s Casual Luxury Hotel": "\u00d6sterreich", "Olivia Balmes Hotel": "Espanya", "Best Western Premier Hotel Couture": "Nederland", "Hilton Amsterdam": "Nederland", "88 Studios": "United Kingdom", "Ozo Hotel": "Nederland", "The Chamberlain": "United Kingdom", "Radisson Blu Hotel Amsterdam": "Nederland", "Britannia International Hotel Canary Wharf": "United Kingdom", "Arbor Hyde Park": "United Kingdom", "Hotel Cavour": "Italia", "The Piccadilly London West End": "United Kingdom", "Mercure Paris Centre Tour Eiffel": "France", "The Tophams Hotel": "United Kingdom", "Hotel Spa Villa Olimpica Suites": "Espa\u00f1a", "Eurostars Cristal Palace": "Espanya", "Hampshire Hotel Amsterdam American": "Nederland", "Radisson Blu Edwardian Kenilworth": "United Kingdom", "Paris Marriott Champs Elysees Hotel": "France", "Hotel Lam e": "\u00d6sterreich", "Hilton London Canary Wharf": "United Kingdom", "Ayre Hotel Gran V a": "Espa\u00f1a", "Golden Tulip Bercy Gare de Lyon 209": "France", "Capri by Fraser Barcelona": "Espa\u00f1a", "Best Western Palm Hotel": "United Kingdom", "DoubleTree by Hilton Hotel London Tower of London": "United Kingdom", "The Drayton Court Hotel": "United Kingdom", "H tel Brighton Esprit de France": "France", "DoubleTree by Hilton London West End": "United Kingdom", "Mercure London Kensington Hotel": "United Kingdom", "Boutiquehotel Das Tyrol": "\u00d6sterreich", "NH Milano Touring": "Italia", "Club Quarters Hotel St Paul s": "United Kingdom", "art otel Amsterdam": "Nederland", "Park Grand London Kensington": "United Kingdom", "Hotel de France Wien": "\u00d6sterreich", "Glam Milano": "Italia", "Urban Lodge Hotel": "Nederland", "Arion Cityhotel Vienna und Appartements": "\u00d6sterreich", "Norfolk Towers Paddington": "United Kingdom", "Col n Hotel Barcelona": "Espanya", "The Rockwell": "United Kingdom", "Novotel London West": "United Kingdom", "Hampton by Hilton Amsterdam Centre East": "Nederland", "Park Plaza Westminster Bridge London": "United Kingdom", "Shepherd s Bush Boutique Hotel": "United Kingdom", "Austria Trend Hotel Ananas Wien": "\u00d6sterreich", "The Sumner Hotel": "United Kingdom", "Henley House Hotel": "United Kingdom", "The Montcalm At Brewery London City": "United Kingdom", "Pestana Chelsea Bridge Hotel Spa": "United Kingdom", "Hotel West End": "France", "WestCord Fashion Hotel Amsterdam": "Nederland", "Best Western Hotel Pension Arenberg Wien Zentrum": "\u00d6sterreich", "Acta Atrium Palace": "Espanya", "The RE London Shoreditch": "United Kingdom", "Holiday Inn Paris Notre Dame": "France", "Holiday Inn London Wembley": "United Kingdom", "Hotel Esther a": "Nederland", "TownHouse 12": "Italia", "Millennium Gloucester Hotel London": "United Kingdom", "Best Western Mornington Hotel Hyde Park": "United Kingdom", "Saint James Albany Paris Hotel Spa": "France", "Luxury Suites Amsterdam": "Nederland", "Amba Hotel Marble Arch": "United Kingdom", "Vincci Bit": "Espanya", "NH Collection Amsterdam Barbizon Palace": "Nederland", "DoubleTree by Hilton Amsterdam Centraal Station": "Nederland", "The Chelsea Harbour Hotel": "United Kingdom", "Washington Mayfair Hotel": "United Kingdom", "Alma Barcelona GL": "Espanya", "Mercure Paris Terminus Nord": "France", "Novotel London Greenwich": "United Kingdom", "The Park Grand London Paddington": "United Kingdom", "Hilton London Green Park": "United Kingdom", "Ace Hotel London Shoreditch": "United Kingdom", "The Langham London": "United Kingdom", "Occidental Atenea Mar Adults Only": "Espanya", "The Queens Gate Hotel": "United Kingdom", "Hotel Santa Marta Suites": "Italia", "Hilton London Wembley": "United Kingdom", "DoubleTree by Hilton London Ealing": "United Kingdom", "Holiday Inn Amsterdam Arena Towers": "Nederland", "The Cumberland A Guoman Hotel": "United Kingdom", "Aloft London Excel": "United Kingdom", "The Waldorf Hilton": "United Kingdom", "Hotel du Vin Cannizaro House Wimbledon": "United Kingdom", "Great St Helen Hotel": "United Kingdom", "Le Narcisse Blanc Spa": "France", "Best Western Seraphine Kensington Olympia": "United Kingdom", "Austria Trend Hotel Schloss Wilhelminenberg Wien": "\u00d6sterreich", "Catalonia Born": "Espa\u00f1a", "Le Meridien Piccadilly": "United Kingdom", "Grange Tower Bridge Hotel": "United Kingdom", "Hotel Vueling Bcn by HC": "Espa\u00f1a", "Inntel Hotels Amsterdam Centre": "Nederland", "Le Relais Madeleine": "France", "DoubleTree by Hilton London Victoria": "United Kingdom", "COQ Hotel Paris": "France", "South Place Hotel": "United Kingdom", "Batty Langley s": "United Kingdom", "Hilton London Hyde Park": "United Kingdom", "Blakemore Hyde Park": "United Kingdom", "Henry VIII": "United Kingdom", "H tel des Academies et des Arts": "France", "Millennium Copthorne Hotels at Chelsea Football Club": "United Kingdom", "Barcelona Princess": "Espanya", "Holiday Inn Paris Gare de Lyon Bastille": "France", "The Premier Notting Hill": "United Kingdom", "Atahotel Contessa Jolanda": "Italia", "NH Carlton Amsterdam": "Nederland", "Best Western Blue Tower Hotel": "Nederland", "Rydges Kensington Hotel": "United Kingdom", "Royal Garden Hotel": "United Kingdom", "TWO Hotel Barcelona by Axel 4 Sup Adults Only": "Espanya", "Residence Henri IV": "France", "Atlantis Hotel Vienna": "\u00d6sterreich", "The Levin Hotel": "United Kingdom", "Mercure Hotel Amsterdam West": "Nederland", "Hotel SB Diagonal Zero Barcelona 4 Sup": "Espanya", "Grand Royale London Hyde Park": "United Kingdom", "Hotel Stefanie": "\u00d6sterreich", "Royal Hotel Champs Elys es": "France", "The London EDITION": "United Kingdom", "Op ra Marigny": "France", "St George s Hotel Wembley": "United Kingdom", "Novotel London Blackfriars": "United Kingdom", "Bulgari Hotel London": "United Kingdom", "Doubletree By Hilton London Greenwich": "United Kingdom", "The One Barcelona GL": "Espanya", "London Marriott Maida Vale": "United Kingdom", "Park Avenue Baker Street": "United Kingdom", "K K Hotel George": "United Kingdom", "Doubletree by Hilton London Kensington": "United Kingdom", "INK Hotel Amsterdam MGallery by Sofitel": "Nederland", "Shaftesbury Suites London Marble Arch": "United Kingdom", "Sixtytwo Hotel": "Espanya", "citizenM Amsterdam": "Nederland", "Saint SHERMIN bed breakfast champagne": "\u00d6sterreich", "The Lodge Hotel Putney": "United Kingdom", "Hotel Michelangelo": "Italia", "Paris Marriott Opera Ambassador Hotel": "France", "The Montcalm Marble Arch": "United Kingdom", "Good Hotel London": "United Kingdom", "The Mandeville Hotel": "United Kingdom", "London Marriott Hotel Marble Arch": "United Kingdom", "Hotel Odeon Saint Germain": "France", "Club Quarters Hotel Lincoln s Inn Fields": "United Kingdom", "La Tremoille Paris": "France", "Grange St Paul s Hotel": "United Kingdom", "The Gates Diagonal Barcelona": "Espanya", "citizenM Tower of London": "United Kingdom", "Antares Hotel Rubens": "Italia", "Hotel Johann Strauss": "\u00d6sterreich", "Park Lane Mews Hotel": "United Kingdom", "Jaz Amsterdam": "Nederland", "Jumeirah Lowndes Hotel": "United Kingdom", "Park Grand Paddington Court": "United Kingdom", "Villa Beaumarchais": "France", "Catalonia Atenas": "Espa\u00f1a", "NH Collection Milano President": "Italia", "Copthorne Tara Hotel London Kensington": "United Kingdom", "Bianca Maria Palace Hotel": "Italia", "The Grosvenor": "United Kingdom", "Starhotels Echo": "Italia", "M by Montcalm Shoreditch London Tech City": "United Kingdom", "Holiday Inn London Brent Cross": "United Kingdom", "Fletcher Hotel Amsterdam": "Nederland", "Warwick Paris Former Warwick Champs Elysees ": "France", "Pertschy Palais Hotel": "\u00d6sterreich", "Club Quarters Hotel Gracechurch": "United Kingdom", "The Harmonie Vienna": "\u00d6sterreich", "H tel Regina": "France", "Novotel London Excel": "United Kingdom", "The Bailey s Hotel London": "United Kingdom", "The Hoxton Shoreditch": "United Kingdom", "H tel Westminster": "France", "The Square Milano Duomo": "Italia", "Terrass H tel Montmartre by MH": "France", "Mercure Amsterdam Sloterdijk Station": "Nederland", "Apex Temple Court Hotel": "United Kingdom", "Negresco Princess 4 Sup": "Espanya", "Hilton London Metropole": "United Kingdom", "St Martins Lane A Morgans Original": "United Kingdom", "Durrants Hotel": "United Kingdom", "Hotel Die Port van Cleve": "Nederland", "Twenty Nevern Square Hotel": "United Kingdom", "Radisson Blu Portman Hotel London": "United Kingdom", "Clayton Hotel Chiswick": "United Kingdom", "The Whitechapel": "United Kingdom", "Crowne Plaza London Kensington": "United Kingdom", "Apollo Hotel Amsterdam": "Nederland", "Hotel Roemer Amsterdam": "Nederland", "H tel Duc De St Simon": "France", "Pullman London St Pancras": "United Kingdom", "Royal Ramblas": "Espanya", "St Ermin s Hotel Autograph Collection": "United Kingdom", "Pulitzer Amsterdam": "Nederland", "St James Court A Taj Hotel London": "United Kingdom", "Strand Palace Hotel": "United Kingdom", "St James Hotel Club Mayfair": "United Kingdom", "Arthotel ANA Boutique Six": "\u00d6sterreich", "Millennium Hotel London Knightsbridge": "United Kingdom", "Catalonia Ramblas 4 Sup": "Espanya", "Novotel Paris Gare De Lyon": "France", "Catalonia Plaza Catalunya": "Espanya", "Millennium Hotel London Mayfair": "United Kingdom", "DoubleTree by Hilton London Docklands Riverside": "United Kingdom", "Worldhotel Cristoforo Colombo": "Italia", "NH Barcelona Stadium": "Espanya", "Arthotel ANA Prime": "\u00d6sterreich", "Avenida Palace": "Espa\u00f1a", "Adria Boutique Hotel": "United Kingdom", "The Ned": "United Kingdom", "Rosa Grand Milano Starhotels Collezione": "Italia", "Amsterdam Marriott Hotel": "Nederland", "NH Amsterdam Schiller": "Nederland", "Best Western Op ra Batignolles": "France", "citizenM London Shoreditch": "United Kingdom", "The Student Hotel Amsterdam City": "Nederland", "Grand Hotel Wien": "\u00d6sterreich", "Francois 1er": "France", "Hotel Manzoni": "Italia", "DO CO Hotel Vienna": "\u00d6sterreich", "Renaissance Amsterdam Hotel": "Nederland", "London Suites": "United Kingdom", "Andreola Central Hotel": "Italia", "Le M ridien Etoile": "France", "Radisson Blu Edwardian New Providence Wharf": "United Kingdom", "Dorsett Shepherds Bush": "United Kingdom", "25hours Hotel beim MuseumsQuartier": "\u00d6sterreich", "Abba Garden": "Espanya", "Hotel Tiziano Park Vita Parcour Gruppo MiniHotels": "Italia", "Maison Albar Hotel Paris C line": "France", "Maison Souquet": "France", "H10 Marina Barcelona": "Espanya", "Le Saint Hotel Paris": "France", "Leonardo Hotel Vienna": "\u00d6sterreich", "The Ritz London": "United Kingdom", "The Hub Hotel": "Italia", "Intercontinental London The O2": "United Kingdom", "Hotel Palace GL": "Espanya", "Hotel Auriga": "Italia", "H tel R de Paris Boutique Hotel": "France", "Hilton London Tower Bridge": "United Kingdom", "Thistle Holborn The Kingsley": "United Kingdom", "Mayflower Hotel Apartments": "United Kingdom", "H tel Bedford": "France", "The Connaught": "United Kingdom", "Conrad London St James": "United Kingdom", "Petit Palace Boqueria Garden": "Espanya", "Hotel Le Six": "France", "Grange Wellington Hotel": "United Kingdom", "Arthotel ANA Westbahn": "\u00d6sterreich", "Hilton London Paddington": "United Kingdom", "Hotel Villa Emilia": "Espanya", "La Maison Champs Elys es": "France", "Hotel Xenia Autograph Collection": "United Kingdom", "Barcel Raval": "Espanya", "Best Western Plus Hotel Galles": "Italia", "Palais Hansen Kempinski Vienna": "\u00d6sterreich", "Sall s Hotel Pere IV": "Espanya", "The Hoxton Holborn": "United Kingdom", "The Tower A Guoman Hotel": "United Kingdom", "London Marriott Hotel West India Quay": "United Kingdom", "NH Amsterdam Noord": "Nederland", "Le Meridien Vienna": "\u00d6sterreich", "Palais Coburg Residenz": "\u00d6sterreich", "Hotel Sacher Wien": "\u00d6sterreich", "Sloane Square Hotel": "United Kingdom", "Boundary Rooms Suites": "United Kingdom", "Radisson Blu Edwardian Grafton": "United Kingdom", "NH Hesperia Barcelona del Mar": "Espanya", "Hotel Margot House": "Espanya", "Shaftesbury Premier London Paddington": "United Kingdom", "Grupotel Gran Via 678": "Espanya", "Thistle Kensington Gardens": "United Kingdom", "Megaro Hotel": "United Kingdom", "AZIMUT Hotel Vienna": "\u00d6sterreich", "Austria Trend Hotel Park Royal Palace Vienna": "\u00d6sterreich", "The Marble Arch London": "United Kingdom", "Hotel Sanpi Milano": "Italia", "Eurostars Grand Marina Hotel GL": "Espanya", "Steigenberger Hotel Herrenhof": "\u00d6sterreich", "Corus Hotel Hyde Park": "United Kingdom", "H tel Gustave": "France", "Amba Hotel Charing Cross": "United Kingdom", "Gran Hotel Torre Catalunya": "Espanya", "Best Western PLUS Epping Forest": "United Kingdom", "H tel de la Bourdonnais": "France", "Park Plaza Victoria Amsterdam": "Nederland", "Park Plaza London Waterloo": "United Kingdom", "Hotel OFF Paris Seine": "France", "H10 London Waterloo": "United Kingdom", "Hampshire Hotel Rembrandt Square Amsterdam": "Nederland", "Shangri La Hotel at The Shard London": "United Kingdom", "The Grand at Trafalgar Square": "United Kingdom", "Austria Trend Parkhotel Sch nbrunn Wien": "\u00d6sterreich", "Goodenough Club": "United Kingdom", "Grand Hotel Saint Michel": "France", "Grange City Hotel": "United Kingdom", "Hotel Royal": "\u00d6sterreich", "Pullman Barcelona Skipper": "Espanya", "The Chesterfield Mayfair": "United Kingdom", "Holiday Inn London Bloomsbury": "United Kingdom", "Courtyard by Marriott Amsterdam Arena Atlas": "Nederland", "Best Western Plus Seraphine Hammersmith Hotel": "United Kingdom", "Le 123 S bastopol Astotel": "France", "Novotel London Canary Wharf": "United Kingdom", "NH Amsterdam Centre": "Nederland", "Park Grand London Lancaster Gate": "United Kingdom", "Nottingham Place Hotel": "United Kingdom", "Pullman Paris Tour Eiffel": "France", "Hilton London Olympia": "United Kingdom", "Hotel Regina": "Espanya", "BEST WESTERN PLUS Amedia Wien": "\u00d6sterreich", "Best Western Premier Op ra Opal": "France", "The Royal Horseguards": "United Kingdom", "Amadi Panorama Hotel": "Nederland", "Hotel Indigo Barcelona Plaza Catalunya": "Espa\u00f1a", "H tel De Castiglione": "France", "Best Western The Boltons Hotel London Kensington": "United Kingdom", "Brunelleschi Hotel": "Italia", "Bcn Urban Hotels Gran Rosellon": "Espanya", "Novotel Amsterdam City": "Nederland", "Mercure London Paddington Hotel": "United Kingdom", "The Justin James Hotel": "United Kingdom", "My Home In Paris": "France", "Amadi Park Hotel": "Nederland", "Radisson Blu Edwardian Berkshire": "United Kingdom", "United Lodge Hotel and Apartments": "United Kingdom", "Axel Hotel Barcelona Urban Spa Adults Only": "Espa\u00f1a", "Hotel Sans Souci Wien": "\u00d6sterreich", "Starhotels Anderson": "Italia", "The Zetter Townhouse Clerkenwell": "United Kingdom", "WestCord Art Hotel Amsterdam 4 stars": "Nederland", "H10 Casanova": "Espanya", "London Marriott Hotel Grosvenor Square": "United Kingdom", "Amarante Champs Elys es": "France", "Ramada Apollo Amsterdam Centre": "Nederland", "Hotel Erzherzog Rainer": "\u00d6sterreich", "Holiday Inn London West": "United Kingdom", "DoubleTree By Hilton London Excel": "United Kingdom", "IH Hotels Milano Lorenteggio": "Italia", "Novotel London Wembley": "United Kingdom", "Hotel Landhaus Fuhrgassl Huber": "\u00d6sterreich", "Holiday Inn Vienna City": "\u00d6sterreich", "Best Western Premier Hotel Dante": "Espanya", "Crowne Plaza London Docklands": "United Kingdom", "HCC St Moritz": "Espanya", "Hotel d Orsay Esprit de France": "France", "Hotel Pulitzer": "Espanya", "Park Grand London Hyde Park": "United Kingdom", "Hotel Milano Scala": "Italia", "St Pancras Renaissance Hotel London": "United Kingdom", "Hotel Ambassador": "\u00d6sterreich", "Mercure Hotel Amsterdam City South": "Nederland", "Holiday Inn Paris Montmartre": "France", "The Westbourne Hyde Park": "United Kingdom", "citizenM London Bankside": "United Kingdom", "The Belgrave Hotel": "United Kingdom", "Best Western Atlantic Hotel": "Italia", "Hotel Schild": "\u00d6sterreich", "Holiday Inn London Oxford Circus": "United Kingdom", "Bloomsbury Palace Hotel": "United Kingdom", "AC Hotel Sants a Marriott Lifestyle Hotel": "Espanya", "Mercure London Hyde Park": "United Kingdom", "Hotel Spadari Al Duomo": "Italia", "Hotel ViennArt am Museumsquartier": "\u00d6sterreich", "Grand Hotel Amr th Amsterdam": "Nederland", "Auteuil Tour Eiffel": "France", "Starhotels Business Palace": "Italia", "Rosewood London": "United Kingdom", "Le Senat": "France", "Hotel Mailberger Hof": "\u00d6sterreich", "Radisson Blu Edwardian Mercer Street": "United Kingdom", "Acevi Villarroel": "Espanya", "Corinthia Hotel London": "United Kingdom", "Ilunion Almirante": "Espanya", "Hotel The Serras": "Espa\u00f1a", "The Mirror Barcelona": "Espanya", "Millennium Hotel Paris Opera": "France", "The Corner Hotel": "Espanya", "Novotel Wien City": "\u00d6sterreich", "STRAF a Member of Design Hotels ": "Italia", "Park Plaza Sherlock Holmes London": "United Kingdom", "Madeleine Plaza": "France", "Room Mate Aitana": "Nederland", "Austria Trend Hotel Doppio Wien": "\u00d6sterreich", "Au Manoir Saint Germain": "France", "Malmaison London": "United Kingdom", "Oceania Paris Porte De Versailles": "France", "Park Plaza Victoria London": "United Kingdom", "Bermondsey Square Hotel A Bespoke Hotel": "United Kingdom", "The Rookery": "United Kingdom", "H10 Urquinaona Plaza": "Espanya", "The Laslett": "United Kingdom", "The Westbridge Hotel": "United Kingdom", "Hotel Da Vinci": "Italia", "Sir Albert Hotel": "Nederland", "Hotel Monsieur": "France", "Hotel degli Arcimboldi": "Italia", "The Montague On The Gardens": "United Kingdom", "Pol Grace Hotel": "Espanya", "JUFA Hotel Wien": "\u00d6sterreich", "The Victoria": "United Kingdom", "Courthouse Hotel London": "United Kingdom", "Hotel Casa Fuster G L Monumento": "Espanya", "TheWesley": "United Kingdom", "Hotel 4 Barcelona": "Espanya", "Novotel London Paddington": "United Kingdom", "Acta CITY47": "Espanya", "Hallmark Hotel London Chigwell Prince Regent": "United Kingdom", "Hilton London Bankside": "United Kingdom", "Hotel De Hallen": "Nederland", "The Principal London": "United Kingdom", "Hotel Cafe Royal": "United Kingdom", "Gran Hotel La Florida": "Espa\u00f1a", "The Ritz Carlton Vienna": "\u00d6sterreich", "Park Plaza London Park Royal": "United Kingdom", "Hotel 1898": "Espanya", "H tel Mathis Elys es": "France", "Hotel Mozart": "Italia", "Holiday Inn London Regent s Park": "United Kingdom", "The Zetter Hotel": "United Kingdom", "Fleming s Selection Hotel Wien City": "\u00d6sterreich", "Hotel Derby": "Espanya", "NH Collection Wien Zentrum": "\u00d6sterreich", "Hilton London Angel Islington": "United Kingdom", "Apollofirst Boutique Hotel": "Nederland", "H tel De Sers Champs Elys es Paris": "France", "K West Hotel Spa": "United Kingdom", "Grange Fitzrovia Hotel": "United Kingdom", "H tel Hor": "France", "Mercure Paris Porte De Versailles Expo": "France", "Hotel Atlanta": "\u00d6sterreich", "Eurostars Bcn Design": "Espanya", "Chateau Frontenac": "France", "Starhotels Ritz": "Italia", "Hotel Monge": "France", "D clic Hotel": "France", "Senator Barcelona Spa Hotel": "Espanya", "Mercure Paris Opera Louvre": "France", "Saint Georges Hotel": "United Kingdom", "Sofitel Paris Arc De Triomphe": "France", "Ilunion Barcelona": "Espanya", "Hotel Vondel Amsterdam": "Nederland", "Hotel Marignan Champs Elys es": "France", "H10 Cubik 4 Sup": "Espanya", "Vincci Maritimo": "Espanya", "Austria Trend Hotel Bosei Wien": "\u00d6sterreich", "Arbor City": "United Kingdom", "Bassano": "France", "Hotel Trianon Rive Gauche": "France", "Andaz London Liverpool Street": "United Kingdom", "Radisson Blu Edwardian Sussex": "United Kingdom", "Mimi s Hotel Soho": "United Kingdom", "Best Western Hotel Montmartre Sacr Coeur": "France", "Hyatt Regency Paris Etoile": "France", "Mandarin Oriental Hyde Park London": "United Kingdom", "Park Plaza Vondelpark Amsterdam": "Nederland", "Le Pigalle Hotel": "France", "Apex London Wall Hotel": "United Kingdom", "Staybridge Suites London Stratford": "United Kingdom", "Expo Hotel Barcelona": "Espanya", "Gardette Park Hotel": "France", "H tel L Echiquier Op ra Paris MGallery by Sofitel": "France", "Hotel Am Parkring": "\u00d6sterreich", "Ca Bianca Hotel Corte Del Naviglio": "Italia", "Novotel Paris Vaugirard Montparnasse": "France", "Andaz Amsterdam Prinsengracht A Hyatt Hotel": "Nederland", "UNA Maison Milano": "Italia", "The Toren": "Nederland", "Le Marceau Bastille": "France", "Innkeeper s Lodge London Greenwich": "United Kingdom", "Ambassade Hotel": "Nederland", "Kensington House Hotel": "United Kingdom", "Shaftesbury Metropolis London Hyde Park": "United Kingdom", "Hotel Eden": "France", "Club Quarters Hotel Trafalgar Square": "United Kingdom", "Petit Palais Hotel De Charme": "Italia", "H tel du Minist re": "France", "Hotel Vignon": "France", "The Hoxton Amsterdam": "Nederland", "Haymarket Hotel": "United Kingdom", "K K Palais Hotel": "\u00d6sterreich", "Hotel Arena": "Nederland", "Lansbury Heritage Hotel": "United Kingdom", "Hotel Indigo London Paddington": "United Kingdom", "Lyric H tel Paris": "France", "The Pelham Starhotels Collezione": "United Kingdom", "Hotel 82 London": "United Kingdom", "The Soho Hotel": "United Kingdom", "Hotel Okura Amsterdam": "Nederland", "UNA Hotel Cusani": "Italia", "Conservatorium Hotel": "Nederland", "Hotel Midmost": "Espa\u00f1a", "Holiday Inn London Camden Lock": "United Kingdom", "Hotel Claridge Paris": "France", "Grange White Hall Hotel": "United Kingdom", "Austria Trend Hotel Europa Wien": "\u00d6sterreich", "H tel D Aubusson": "France", "Hotel Am Schubertring": "\u00d6sterreich", "Hotel Capricorno": "\u00d6sterreich", "H tel Balzac": "France", "H tel Bel Ami": "France", "NH London Kensington": "United Kingdom", "Grand Hotel Downtown": "Nederland", "Fleming s Conference Hotel Wien": "\u00d6sterreich", "The Stafford London": "United Kingdom", "Crowne Plaza London The City": "United Kingdom", "Novotel Paris Centre Gare Montparnasse": "France", "Le Cinq Codet": "France", "Hotel JL No76": "Nederland", "Hotel Beethoven Wien": "\u00d6sterreich", "Bilderberg Garden Hotel": "Nederland", "H10 Casa Mimosa 4 Sup": "Espanya", "Holiday Inn London Mayfair": "United Kingdom", "Hotel Manin": "Italia", "Enterprise Hotel Design Boutique": "Italia", "Hotel Espa a Ramblas": "Espanya", "Holiday Inn Paris Elys es": "France", "Hotel Serhs Rivoli Rambla": "Espanya", "Imperial Riding School Renaissance Vienna Hotel": "\u00d6sterreich", "M venpick Hotel Amsterdam City Centre": "Nederland", "ARCOTEL Wimberger": "\u00d6sterreich", "Catalonia Catedral": "Espanya", "H tel Beauchamps": "France", "Danubius Hotel Regents Park": "United Kingdom", "Holiday Inn London Whitechapel": "United Kingdom", "InterContinental London Park Lane": "United Kingdom", "St Paul s Hotel": "United Kingdom", "Hotel Pulitzer Paris": "France", "Hilton Vienna": "\u00d6sterreich", "Hotel Berna": "Italia", "Idea Hotel Milano San Siro": "Italia", "Hotel Nestroy Wien": "\u00d6sterreich", "NH Collection Barcelona Gran Hotel Calder n": "Espa\u00f1a", "Olivia Plaza Hotel": "Espanya", "Hotel V Fizeaustraat": "Nederland", "Hotel Best Western PLUS Alfa Aeropuerto": "Espa\u00f1a", "Roger de Ll ria": "Espanya", "Crowne Plaza London Battersea": "United Kingdom", "DoubleTree by Hilton London Islington": "United Kingdom", "Forest Hill Paris la Villette": "France", "Apex City Of London Hotel": "United Kingdom", "The Guesthouse Vienna": "\u00d6sterreich", "Hotel Das Tigra": "\u00d6sterreich", "Hotel K nig von Ungarn": "\u00d6sterreich", "Hotel Kavalier": "\u00d6sterreich", "Park Plaza London Riverbank": "United Kingdom", "De Vere Devonport House": "United Kingdom", "Condes de Barcelona": "Espanya", "Sunotel Club Central": "Espa\u00f1a", "Novotel Paris Centre Tour Eiffel": "France", "Hotel Eug ne en Ville": "France", "H tel de La Tamise Esprit de France": "France", "ME London by Melia": "United Kingdom", "Le Parisis Paris Tour Eiffel": "France", "ADI Hotel Poliziano Fiera": "Italia", "Best Western Plus de Neuville Arc de Triomphe": "France", "London Marriott Hotel Regents Park": "United Kingdom", "Rubens At The Palace": "United Kingdom", "The Park Tower Knightsbridge a Luxury Collection Hotel": "United Kingdom", "Best Western Plus Hotel Felice Casati": "Italia", "H10 Metropolitan 4 Sup": "Espanya", "Napoleon Paris": "France", "My Bloomsbury": "United Kingdom", "Pullman Paris Montparnasse": "France", "Sunotel Central": "Espanya", "Suite Hotel 900 m zur Oper": "\u00d6sterreich", "Renaissance Paris Vendome Hotel": "France", "K K Hotel Picasso": "Espanya", "Hotel Cavendish": "United Kingdom", "Hotel Domizil": "\u00d6sterreich", "Excelsior Hotel Gallia Luxury Collection Hotel": "Italia", "Royal Passeig de Gracia": "Espanya", "Maison Albar Hotel Paris Op ra Diamond": "France", "Ten Manchester Street Hotel": "United Kingdom", "Austria Trend Hotel Anatol Wien": "\u00d6sterreich", "Crowne Plaza Milan City": "Italia", "The Leonard Hotel": "United Kingdom", "IH Hotels Milano Gioia": "Italia", "Windermere Hotel": "United Kingdom", "NH Collection Amsterdam Doelen": "Nederland", "Grange Holborn Hotel": "United Kingdom", "Chambiges Elys es": "France", "IH Hotels Milano Ambasciatori": "Italia", "Hotel Indigo London Tower Hill": "United Kingdom", "Sheraton Grand London Park Lane": "United Kingdom", "Derag Livinghotel Kaiser Franz Joseph Vienna": "\u00d6sterreich", "Best Western Plus Hotel Blue Square": "Nederland", "Silken Gran Hotel Havana": "Espanya", "Hotel City Central": "\u00d6sterreich", "Ayre Hotel Rosell n": "Espanya", "My Chelsea": "United Kingdom", "Gainsborough Hotel": "United Kingdom", "LaGare Hotel Milano Centrale MGallery by Sofitel": "Italia", "Corendon Vitality Hotel Amsterdam": "Nederland", "Hotel Amadeus": "\u00d6sterreich", "Pullman Paris Centre Bercy": "France", "Le Mathurin Hotel Spa": "France", "Catalonia Magdalenes": "Espa\u00f1a", "Art Hotel Navigli": "Italia", "The Ampersand Hotel": "United Kingdom", "Newhotel Roblin": "France", "NH Collection Amsterdam Grand Hotel Krasnapolsky": "Nederland", "Le Pavillon de la Reine Spa": "France", "London Hilton on Park Lane": "United Kingdom", "Hotel Villa Saxe Eiffel": "France", "Hotel La Spezia Gruppo MiniHotel": "Italia", "Novotel Barcelona City": "Espanya", "Hotel D Este": "Italia", "Grange Rochester Hotel": "United Kingdom", "every hotel Piccadilly": "United Kingdom", "Best Western Premier Op ra Faubourg Ex Hotel Jules ": "France", "Hotel SB Icaria Barcelona": "Espanya", "Austria Trend Hotel Astoria Wien": "\u00d6sterreich", "Catalonia Port": "Espanya", "The Westbury A Luxury Collection Hotel Mayfair London": "United Kingdom", "Hotel Casa Camper": "Espanya", "Draycott Hotel": "United Kingdom", "Room Mate Carla": "Espanya", "Little Palace Hotel": "France", "Montcalm Royal London House City of London": "United Kingdom", "Royal Garden Champs Elysees": "France", "Hotel Wandl": "\u00d6sterreich", "Hotel Barcelona Catedral": "Espanya", "Hotel DO Pla a Reial G L ": "Espa\u00f1a", "Room Mate Giulia": "Italia", "Duquesa Suites Barcelona": "Espanya", "Das Opernring Hotel": "\u00d6sterreich", "Rafayel Hotel Spa": "United Kingdom", "Alma Boutique Hotel": "\u00d6sterreich", "Silken Concordia": "Espa\u00f1a", "Nhow Milan": "Italia", "Suites H tel Helzear Montparnasse": "France", "The Colonnade": "United Kingdom", "Best Western Plus Elys e Secret": "France", "Dikker en Thijs Fenice Hotel": "Nederland", "Holiday Inn Paris Gare de l Est": "France", "Fielding Hotel": "United Kingdom", "Best Western Le 18 Paris": "France", "St George Hotel": "United Kingdom", "Grange Strathmore Hotel": "United Kingdom", "Swiss tel Amsterdam": "Nederland", "Hotel Amsterdam De Roode Leeuw": "Nederland", "Select Hotel": "France", "Catalonia Eixample 1864": "Espanya", "Cram": "Espa\u00f1a", "Elys es R gencia": "France", "Senator Hotel Vienna": "\u00d6sterreich", "Hazlitt s": "United Kingdom", "Park Hotel": "Nederland", "Austria Trend Hotel Savoyen Vienna": "\u00d6sterreich", "Ashburn Hotel": "United Kingdom", "Hotel mbit Barcelona": "Espanya", "The Bloomsbury Hotel": "United Kingdom", "Best Western Tour Eiffel Invalides": "France", "Comfort Inn Suites Kings Cross St Pancras": "United Kingdom", "The Rembrandt": "United Kingdom", "Hilton Vienna Plaza": "\u00d6sterreich", "Sina De La Ville": "Italia", "Best Western Premier Kapital Op ra": "France", "Hotel America Barcelona": "Espanya", "Catalonia Square 4 Sup": "Espanya", "Hotel Alimara": "Espanya", "Antares Hotel Accademia": "Italia", "H tel de Varenne": "France", "DoubleTree by Hilton London Chelsea": "United Kingdom", "Appartement Hotel an der Riemergasse": "\u00d6sterreich", "Fairmont Rey Juan Carlos I": "Espa\u00f1a", "DoubleTree by Hilton London Hyde Park": "United Kingdom", "Commodore Hotel": "United Kingdom", "Courthouse Hotel Shoreditch": "United Kingdom", "Austria Trend Hotel Lassalle Wien": "\u00d6sterreich", "Catalonia Passeig de Gr cia 4 Sup": "Espanya", "H tel Monna Lisa Champs Elys es": "France", "Best Western Antares Hotel Concorde": "Italia", "Thistle Trafalgar Square The Royal Trafalgar": "United Kingdom", "Lancaster London": "United Kingdom", "Rathbone": "United Kingdom", "AC Hotel Diagonal L Illa a Marriott Lifestyle Hotel": "Espa\u00f1a", "Park Inn by Radisson Uno City Vienna": "\u00d6sterreich", "The Wittmore Adults Only": "Espa\u00f1a", "Rocco Forte Brown s Hotel": "United Kingdom", "H tel Horset Op ra Best Western Premier Collection": "France", "Grand Visconti Palace": "Italia", "H tel Aiglon Esprit de France": "France", "NH Sants Barcelona": "Espa\u00f1a", "Etoile Saint Ferdinand": "France", "Onix Liceo": "Espanya", "The Exhibitionist Hotel": "United Kingdom", "NH Collection Barcelona Podium": "Espanya", "Vienna Marriott Hotel": "\u00d6sterreich", "H tel Saint Marc": "France", "W Barcelona": "Espa\u00f1a", "The Savoy": "United Kingdom", "Waldorf Madeleine": "France", "Ako Suites Hotel": "Espanya", "Mercer Hotel Barcelona": "Espanya", "Novotel Suites Paris Expo Porte de Versailles": "France", "Milan Marriott Hotel": "Italia", "Edouard 7 Paris Op ra": "France", "Amp re": "France", "Thistle Euston": "United Kingdom", "Best Western Madison Hotel": "Italia", "The Nadler Soho": "United Kingdom", "H tel Regent s Garden": "France", "The Cavendish London": "United Kingdom", "Hotel Les Bains Paris": "France", "Hotel Sunflower": "Italia", "The Academy": "United Kingdom", "Radisson Blu Edwardian Hampshire": "United Kingdom", "Park International Hotel": "United Kingdom", "Rainers Hotel Vienna": "\u00d6sterreich", "Knightsbridge Hotel": "United Kingdom", "The Trafalgar Hilton": "United Kingdom", "H tel Concorde Montparnasse": "France", "Threadneedles Autograph Collection": "United Kingdom", "Ham Yard Hotel": "United Kingdom", "H tel Lancaster Paris Champs Elys es": "France", "InterContinental Wien": "\u00d6sterreich", "Hotel Moonlight": "United Kingdom", "The Nadler Kensington": "United Kingdom", "Jumeirah Carlton Tower": "United Kingdom", "Hotel Mademoiselle": "France", "Mercure Vaugirard Paris Porte De Versailles": "France", "Rochester Champs Elysees": "France", "San Domenico House": "United Kingdom", "Hotel Garbi Millenni": "Espa\u00f1a", "Hollmann Beletage Design Boutique": "\u00d6sterreich", "City Hotel Deutschmeister": "\u00d6sterreich", "9Hotel Republique": "France", "Simm s Hotel": "\u00d6sterreich", "NH Milano Palazzo Moscova": "Italia", "Mercure Paris Montmartre Sacr Coeur": "France", "AC Hotel Barcelona Forum a Marriott Lifestyle Hotel": "Espa\u00f1a", "Villa d Estr es": "France", "Austria Trend Hotel Rathauspark Wien": "\u00d6sterreich", "Hotel Maison FL": "France", "H10 Itaca": "Espanya", "Seven Hotel": "France", "Kingsway Hall Hotel": "United Kingdom", "DoubleTree by Hilton London Westminster": "United Kingdom", "Best Western Le Jardin de Cluny": "France", "H tel Le Walt": "France", "Sofitel London St James": "United Kingdom", "Hampshire Hotel The Manor Amsterdam": "Nederland", "Relais Christine": "France", "Sofitel Legend The Grand Amsterdam": "Nederland", "Grand Pigalle Hotel": "France", "Staunton Hotel B B": "United Kingdom", "La Suite West Hyde Park": "United Kingdom", "Hotel de Nell": "France", "Radisson Blu Edwardian Vanderbilt": "United Kingdom", "Hotel Saint Petersbourg Opera": "France", "Holiday Inn Milan Garibaldi Station": "Italia", "Hotel du Louvre in the Unbound Collection by Hyatt": "France", "Hotel Prinz Eugen": "\u00d6sterreich", "The Hari London": "United Kingdom", "H tel California Champs Elys es": "France", "Melia Barcelona Sarri ": "Espa\u00f1a", "Le Burgundy Paris": "France", "Sina The Gray": "Italia", "La Chambre du Marais": "France", "Radisson Blu Edwardian Bloomsbury Street": "United Kingdom", "NYX Milan": "Italia", "Hotel Vilamar ": "Espanya", "DoubleTree by Hilton Hotel Amsterdam NDSM Wharf": "Nederland", "Flemings Mayfair": "United Kingdom", "La Maison Favart": "France", "Mercure Paris Gare De Lyon TGV": "France", "Buddha Bar Hotel Paris": "France", "Eurostars Ramblas": "Espanya", "H tel Du Jeu De Paume": "France", "45 Park Lane Dorchester Collection": "United Kingdom", "Hotel Bachaumont": "France", "UNA Hotel Century": "Italia", "Best Western Plus 61 Paris Nation Hotel": "France", "Hotel Le Squara": "France", "Golden Tulip Washington Opera": "France", "Sydney House Chelsea": "United Kingdom", "Hotel Balmes": "Espanya", "IH Hotels Milano Watt 13": "Italia", "Novotel Paris Les Halles": "France", "Grange Langham Court Hotel": "United Kingdom", "Barcel Sants": "Espanya", "Golden Tulip Amsterdam Riverside": "Nederland", "Upper Diagonal": "Espanya", "COMO Metropolitan London": "United Kingdom", "Armani Hotel Milano": "Italia", "NH Amsterdam Zuid": "Nederland", "Fifty Four Boutique Hotel": "United Kingdom", "Mercure Paris Arc de Triomphe Etoile": "France", "Duquesa de Cardona": "Espanya", "Grand Ferdinand Vienna Your Hotel In The City Center": "\u00d6sterreich", "Shaftesbury Hyde Park International": "United Kingdom", "London City Suites": "United Kingdom", "Acca Palace": "Italia", "Hotel J ger": "\u00d6sterreich", "K K H tel Cayr Saint Germain des Pr s": "France", "Sansi Diputacio": "Espanya", "Hotel Kaiserin Elisabeth": "\u00d6sterreich", "Vice Versa": "France", "K K Hotel Maria Theresia": "\u00d6sterreich", "Holiday Inn Amsterdam": "Nederland", "Royal Saint Michel": "France", "Ambassadors Bloomsbury": "United Kingdom", "U232 Hotel": "Espanya", "Novotel London Waterloo": "United Kingdom", "UNA Hotel Mediterraneo": "Italia", "Mokinba Hotels Baviera": "Italia", "H tel Diva Opera": "France", "Best Western Hotel Ascot": "Italia", "The Kings Head Hotel": "United Kingdom", "Thistle Hyde Park": "United Kingdom", "The Cleveland": "United Kingdom", "Windsor Hotel Milano": "Italia", "Best Western Premier Faubourg 88": "France", "Great Northern Hotel A Tribute Portfolio Hotel London": "United Kingdom", "Antica Locanda Dei Mercanti": "Italia", "Camperio House Suites Apartments": "Italia", "Ohla Eixample": "Espanya", "Grange Blooms Hotel": "United Kingdom", "Best Western Premier Marais Grands Boulevards": "France", "Hotel Omm": "Espanya", "Georgian House Hotel": "United Kingdom", "Mercure Paris Op ra Faubourg Montmartre": "France", "Le Marcel": "France", "Arioso": "France", "Hotel 55": "United Kingdom", "Grand Hotel Central": "Espanya", "Catalonia La Pedrera": "Espanya", "Landmark London": "United Kingdom", "Novotel Milano Nord Ca Granda": "Italia", "Majestic Hotel Spa": "France", "Le Marquis Eiffel": "France", "Trinit Haussmann": "France", "Ohla Barcelona": "Espanya", "H tel Fabric": "France", "AC Hotel Paris Porte Maillot by Marriott": "France", "The Marylebone Hotel": "United Kingdom", "Qualys Hotel Nasco": "Italia", "Hotel Dei Cavalieri": "Italia", "Hotel Am Konzerthaus Vienna MGallery by Sofitel": "\u00d6sterreich", "Hotel Les Th tres": "France", "H tel Duo": "France", "Hotel Topazz": "\u00d6sterreich", "Hotel Scribe Paris Opera by Sofitel": "France", "Albus Hotel Amsterdam City Centre": "Nederland", "Hotel Ares Eiffel": "France", "H10 Art Gallery 4 Sup": "Espa\u00f1a", "Sercotel Amister Art Hotel Barcelona": "Espa\u00f1a", "Hotel Casa Bonay": "Espanya", "ARCOTEL Kaiserwasser Superior": "\u00d6sterreich", "Melia Paris Notre Dame": "France", "Hotel Ronda Lesseps": "Espanya", "Milan Suite Hotel": "Italia", "Aparthotel Arai 4 Superior": "Espanya", "Schlosshotel R mischer Kaiser": "\u00d6sterreich", "Four Seasons Hotel George V Paris": "France", "The Kensington Hotel": "United Kingdom", "Garden Elys e": "France", "The Levante Parliament A Design Hotel": "\u00d6sterreich", "Sheraton Diana Majestic": "Italia", "NH Milano Machiavelli": "Italia", "Castille Paris Starhotels Collezione": "France", "Carlyle Brera Hotel": "Italia", "Hotel Ciutadella Barcelona": "Espanya", "Radisson Blu Style Hotel Vienna": "\u00d6sterreich", "Best Western Premier Louvre Saint Honor ": "France", "BEST WESTERN Maitrise Hotel Maida Vale": "United Kingdom", "The Cranley Hotel": "United Kingdom", "Hotel Malte Astotel": "France", "Aparthotel Atenea Barcelona": "Espanya", "Starhotels Tourist": "Italia", "Hotel Xanadu": "United Kingdom", "Hotel Romana Residence": "Italia", "The Goring": "United Kingdom", "Hotel Bristol A Luxury Collection Hotel": "\u00d6sterreich", "Hotel V Nesplein": "Nederland", "Hotel Op ra Richepanse": "France", "Mercure Hotel Raphael Wien": "\u00d6sterreich", "Hotel Rathaus Wein Design": "\u00d6sterreich", "Amarante Beau Manoir": "France", "Ramada Plaza Milano": "Italia", "Hilton London Euston": "United Kingdom", "Baglioni Hotel London The Leading Hotels of the World": "United Kingdom", "Best Western Maitrise Hotel Edgware Road": "United Kingdom", "L Hotel Pergol se Paris": "France", "Gallery Hotel": "Espa\u00f1a", "DoubleTree by Hilton Hotel London Marble Arch": "United Kingdom", "NH Wien City": "\u00d6sterreich", "Bilderberg Hotel Jan Luyken": "Nederland", "La Clef Tour Eiffel": "France", "Hotel de Seze": "France", "Platine Hotel Spa": "France", "NH Milano Grand Hotel Verdi": "Italia", "Ch teau Monfort Relais Ch teaux": "Italia", "W12 Rooms": "United Kingdom", "Best Western Ducs de Bourgogne": "France", "The Nadler Victoria": "United Kingdom", "Best Western Nouvel Orl ans Montparnasse": "France", "Eccleston Square Hotel": "United Kingdom", "Hotel Grums Barcelona": "Espa\u00f1a", "Chasse Hotel": "Nederland", "Staybridge Suites London Vauxhall": "United Kingdom", "La Villa des Ternes": "France", "Hotel Le Sainte Beuve": "France", "Arenas Atiram Hotels": "Espanya", "Das Triest Hotel": "\u00d6sterreich", "Uptown Palace": "Italia", "Sofitel Paris Baltimore Tour Eiffel": "France", "Hotel Granados 83": "Espanya", "The Athenaeum": "United Kingdom", "Blakes Hotel": "United Kingdom", "InterContinental Paris Avenue Marceau": "France", "H tel Belloy Saint Germain By Happyculture": "France", "Grange Beauchamp Hotel": "United Kingdom", "Le Grand H tel de Normandie": "France", "H tel San R gis": "France", "Melia White House Hotel": "United Kingdom", "H tel Les Dames du Panth on": "France", "IH Hotels Milano Puccini": "Italia", "Small Luxury Hotel Altstadt Vienna": "\u00d6sterreich", "Le Tsuba Hotel": "France", "Best Western S vres Montparnasse": "France", "Crowne Plaza Paris R publique": "France", "Best Western Premier Kaiserhof Wien": "\u00d6sterreich", "Idol Hotel": "France", "Catalonia Barcelona Plaza": "Espa\u00f1a", "Barcel Milan": "Italia", "Sanderson A Morgans Hotel": "United Kingdom", "Element Amsterdam": "Nederland", "Montfleuri": "France", "Hotel Daniel Vienna": "\u00d6sterreich", "Montagu Place Hotel": "United Kingdom", "H tel Original Paris": "France", "Hotel Saint Dominique": "France", "NH City Centre Amsterdam": "Nederland", "Hotel Bellevue Wien": "\u00d6sterreich", "Hyatt Regency London The Churchill": "United Kingdom", "Hotel Bagu s": "Espanya", "H tel La Comtesse by Elegancia": "France", "Hilton Diagonal Mar Barcelona": "Espanya", "Hotel Galileo": "Italia", "W London Leicester Square": "United Kingdom", "Hotel Carrobbio": "Italia", "Dutch Design Hotel Artemis": "Nederland", "Klima Hotel Milano Fiere": "Italia", "H tel Da Vinci Spa": "France", "Okko Hotels Paris Porte De Versailles": "France", "Westside Arc de Triomphe Hotel": "France", "The Pillar Hotel": "United Kingdom", "Boutique Hotel Notting Hill": "Nederland", "Hotel Schani Wien": "\u00d6sterreich", "Hotel Arts Barcelona": "Espa\u00f1a", "Eurostars Embassy": "\u00d6sterreich", "The Yard Milano": "Italia", "Milestone Hotel Kensington": "United Kingdom", "H tel Cristal Champs Elys es": "France", "Exe Laietana Palace": "Espa\u00f1a", "H tel Paris Bastille Boutet MGallery by Sofitel": "France", "Hilton Garden Inn Milan North": "Italia", "Villa Opera Drouot": "France", "Hotel Well and Come": "Espanya", "Senato Hotel Milano": "Italia", "Hotel Palais Strudlhof": "\u00d6sterreich", "Hotel Miramar Barcelona GL": "Espanya", "ME Milan Il Duca": "Italia", "Catalonia Diagonal Centro": "Espa\u00f1a", "Hotel Maison Ath n e": "France", "Four Seasons Hotel London at Park Lane": "United Kingdom", "Savoy Hotel Amsterdam": "Nederland", "Acad mie H tel Saint Germain": "France", "Courtyard by Marriott Vienna Prater Messe": "\u00d6sterreich", "Sofitel Vienna Stephansdom": "\u00d6sterreich", "Best Western Aulivia Op ra": "France", "Hotel Mentana": "Italia", "The Beaufort": "United Kingdom", "Mandarin Oriental Milan": "Italia", "H tel Madison by MH": "France", "NH Amsterdam Caransa": "Nederland", "Pakat Suites Hotel": "\u00d6sterreich", "First Hotel Paris Tour Eiffel": "France", "The Park City Grand Plaza Kensington Hotel": "United Kingdom", "Four Seasons Hotel Milano": "Italia", "1K Hotel": "France", "NH Wien Belvedere": "\u00d6sterreich", "Le Tourville Eiffel": "France", "Le Belmont Champs Elys es": "France", "Best Western Premier Trocadero La Tour": "France", "Hotel Portello Gruppo Minihotel": "Italia", "Mercure Vienna First": "\u00d6sterreich", "Hotel G tico": "Espanya", "Hilton Vienna Danube Waterfront": "\u00d6sterreich", "Villa Panth on": "France", "The Abbey Court Notting Hill": "United Kingdom", "Attica 21 Barcelona Mar": "Espanya", "Novotel London City South": "United Kingdom", "The Curtain": "United Kingdom", "The Beaumont Hotel": "United Kingdom", "NH Collection Barcelona Constanza": "Espanya", "Crowne Plaza London Ealing": "United Kingdom", "InterContinental Paris Le Grand": "France", "Hilton Milan": "Italia", "H10 Universitat": "Espanya", "Derby Alma": "France", "H tel de Jos phine BONAPARTE": "France", "London Marriott Hotel County Hall": "United Kingdom", "Mercure Secession Wien": "\u00d6sterreich", "The Henrietta Hotel": "United Kingdom", "Hotel Neri": "Espanya", "Mercer House B ria BCN": "Espanya", "H tel de Banville": "France", "Mill sime H tel": "France", "Hotel La Villa Saint Germain Des Pr s": "France", "Les Jardins De La Villa Spa": "France", "H tel Th r se": "France", "Grosvenor House A JW Marriott Hotel": "United Kingdom", "Novotel London Tower Bridge": "United Kingdom", "The Arch London": "United Kingdom", "Hotel Le Mareuil": "France", "Mercure Wien Zentrum": "\u00d6sterreich", "Aparthotel Mariano Cubi Barcelona": "Espa\u00f1a", "Bentley London": "United Kingdom", "Palazzo Parigi Hotel Grand Spa Milano": "Italia", "Roomz Vienna": "\u00d6sterreich", "Eurostars Monumental": "Espanya", "Claris Hotel Spa GL": "Espa\u00f1a", "Boscolo Milano Autograph Collection": "Italia", "H tel Baume": "France", "B Montmartre": "France", "Holiday Inn Paris Saint Germain des Pr s": "France", "H tel des Champs Elys es": "France", "41": "United Kingdom", "NH Amsterdam Museum Quarter": "Nederland", "H tel Regina Op ra Grands Boulevards": "France", "Hotel Champs Elys es Friedland by Happyculture": "France", "Petit Palace Museum": "Espanya", "Canal House": "Nederland", "IntercityHotel Wien": "\u00d6sterreich", "One Aldwych": "United Kingdom", "H10 Port Vell 4 Sup": "Espa\u00f1a", "Best Western Hotel Astoria": "Italia", "Hotel Mercure Wien Westbahnhof": "\u00d6sterreich", "Evenia Rossello": "Espanya", "Paddington Court Executive Rooms": "United Kingdom", "Golden Tulip Opera de Noailles": "France", "FourSide Hotel Suites Vienna": "\u00d6sterreich", "Hotel Dieci": "Italia", "Aparthotel Adagio Vienna City": "\u00d6sterreich", "Prince de Galles a Luxury Collection hotel Paris": "France", "Hotel Park Lane Paris": "France", "Mercure Grand Hotel Biedermeier Wien": "\u00d6sterreich", "Royal Saint Honore": "France", "Grange Clarendon Hotel": "United Kingdom", "Chiswick Rooms": "United Kingdom", "The College Hotel": "Nederland", "H tel Champs lys es Plaza": "France", "Splendid Etoile": "France", "Suites H tel Helzear Champs Elys es": "France", "Maison Albar H tel Paris Champs Elys es ex Mac Mahon ": "France", "Catalonia Rigoletto": "Espanya", "Crowne Plaza Barcelona Fira Center": "Espa\u00f1a", "Molitor Paris MGallery by Sofitel": "France", "Hotel Carlton s Montmartre": "France", "NH Danube City": "\u00d6sterreich", "Best Western Hotel City": "Italia", "Mercure Paris Alesia": "France", "Strandhotel Alte Donau": "\u00d6sterreich", "Hotel Bristol": "Italia", "ADI Doria Grand Hotel": "Italia", "Banke H tel": "France", "Victoires Opera": "France", "Best Western Premier Op ra Li ge": "France", "Catalonia Barcelona 505": "Espanya", "Hotel L Antoine": "France", "Alexandra Barcelona A DoubleTree by Hilton": "Espanya", "Phileas Hotel": "France", "Le Relais Montmartre": "France", "Villa Montparnasse": "France", "Hotel Barcelona Universal": "Espanya", "Courtyard by Marriott Vienna Schoenbrunn": "\u00d6sterreich", "Petit Palace Barcelona": "Espanya", "H tel des Ducs D Anjou": "France", "Maxim Op ra": "France", "Hidden Hotel by Elegancia": "France", "Four Points Sheraton Milan Center": "Italia", "Portobello House": "United Kingdom", "TRYP Paris Op ra": "France", "London Marriott Hotel Park Lane": "United Kingdom", "Best Western Hotel St George": "Italia", "H tel Etoile Saint Honor by Happyculture": "France", "The Bryson Hotel": "United Kingdom", "Grange Buckingham Hotel": "United Kingdom", "H tel Raphael": "France", "Mercure Paris Bastille Marais": "France", "Colombia": "Italia", "Grand H tel Du Palais Royal": "France", "Tryp Barcelona Apolo Hotel": "Espanya", "Hotel Mercure Wien City": "\u00d6sterreich", "Leonardo Hotel Milan City Center": "Italia", "The Zetter Townhouse Marylebone": "United Kingdom", "Graben Hotel": "\u00d6sterreich", "The Portobello Hotel": "United Kingdom", "Melia Barcelona Sky 4 Sup": "Espa\u00f1a", "Hotel Monceau Wagram": "France", "Vincci Mae": "Espanya", "Caesar Hotel": "United Kingdom", "H tel Ad le Jules": "France", "Hotel Principe Di Savoia": "Italia", "Le G n ral H tel": "France", "Hotel du Collectionneur Arc de Triomphe": "France", "Relais Du Louvre": "France", "Best Western Bretagne Montparnasse": "France", "FourSide Hotel Vienna City Center": "\u00d6sterreich", "Holiday Inn Paris Gare Montparnasse": "France", "Seraphine Kensington Gardens Hotel": "United Kingdom", "Hotel Parc Saint Severin Esprit de France": "France", "Charlotte Street Hotel": "United Kingdom", "Guitart Grand Passage": "Espanya", "Eiffel Trocad ro": "France", "NH Hesperia Barcelona Presidente": "Espanya", "London Elizabeth Hotel": "United Kingdom", "Hotel Front Maritim": "Espanya", "Vincci Gala": "Espanya", "Hotel Abbot": "Espanya", "Nell Hotel Suites": "France", "Hotel Barcelona Center": "Espanya", "H tel Crayon Rouge by Elegancia": "France", "Banks Mansion All Inclusive Hotel": "Nederland", "The Royal Park Hotel": "United Kingdom", "Hotel Cambon": "France", "Hotel Mediolanum": "Italia", "Grosvenor House Suites by Jumeirah Living": "United Kingdom", "Baglioni Hotel Carlton The Leading Hotels of the World": "Italia", "Mercure Paris Notre Dame Saint Germain des Pr s": "France", "Primero Primera": "Espa\u00f1a", "Marlin Waterloo": "United Kingdom", "Hotel Pension Baron am Schottentor": "\u00d6sterreich", "Hotel Liberty": "Italia", "Hotel Atmospheres": "France", "Best Western Amiral Hotel": "France", "Melia Paris Champs Elys es": "France", "Hotel Marconi": "Italia", "Zenit Borrell": "Espanya", "Mercure Paris 17 me Saint Lazare Monceau": "France", "pentahotel Vienna": "\u00d6sterreich", "Falkensteiner Hotel Wien Zentrum Schottenfeld": "\u00d6sterreich", "H tel Mansart Esprit de France": "France", "Les Jardins Du Marais": "France", "Park Hyatt Vienna": "\u00d6sterreich", "Mercure Barcelona Condor": "Espanya", "Le M ridien Barcelona": "Espa\u00f1a", "Bradford Elys es Astotel": "France", "The Dylan Amsterdam": "Nederland", "The Westin Palace": "Italia", "H tel Le Bellechasse Saint Germain": "France", "AC Hotel Milano a Marriott Lifestyle Hotel": "Italia", "Le Relais M dicis": "France", "Nu Hotel": "Italia", "H tel La Parizienne by Elegancia": "France", "Novotel Suites Paris Montreuil Vincennes": "France", "Novotel Paris Centre Bercy": "France", "Majestic Hotel Spa Barcelona GL": "Espanya", "L H tel": "France", "Timhotel Op ra Grands Magasins": "France", "Timhotel Op ra Blanche Fontaine": "France", "Hotel Zeitgeist Vienna Hauptbahnhof": "\u00d6sterreich", "The Chess Hotel": "France", "Novotel Suites Paris Nord 18 me": "France", "Monsieur Cadet Hotel Spa Ex Meyerhold Spa ": "France", "Hotel Balmoral": "Espanya", "Hotel Indigo Paris Opera": "France", "Hotel Elys es Bassano": "France", "The Dorchester Dorchester Collection": "United Kingdom", "Hotel Vienna": "\u00d6sterreich", "Hotel Am Stephansplatz": "\u00d6sterreich", "The Capital": "United Kingdom", "Pestana Arena Barcelona": "Espa\u00f1a", "Hotel Clerici": "Italia", "Le 123 Elysees Astotel": "France", "Waldorf Astoria Amsterdam": "Nederland", "Goralska R sidences H tel Paris Bastille": "France", "Radisson Blu Hotel Milan": "Italia", "Hotel Le Chat Noir": "France", "Hotel Duminy Vendome": "France", "Mercure Hotel Amsterdam Centre Canal District": "Nederland", "Wilson Boutique Hotel": "Espanya", "Canary Riverside Plaza Hotel": "United Kingdom", "Hotel Boltzmann": "\u00d6sterreich", "Mercure Paris Bercy Biblioth que": "France", "TownHouse Duomo": "Italia", "Hotel La Place": "United Kingdom", "Atahotel Linea Uno": "Italia", "City Rooms": "\u00d6sterreich", "La Villa Royale": "France", "Residence Du Roy": "France", "H tel Le Marianne": "France", "Relais Saint Jacques": "France", "Eurostars Angli": "Espa\u00f1a", "Der Wilhelmshof": "\u00d6sterreich", "Park Hyatt Paris Vendome": "France", "De L Europe Amsterdam": "Nederland", "Hotel Magna Pars Small Luxury Hotels of the World": "Italia", "Mercure Paris Gare Montparnasse": "France", "Karma Sanctum Soho Hotel": "United Kingdom", "Admiral Hotel": "Italia", "Renaissance Paris Arc de Triomphe Hotel": "France", "LHP Hotel Napoleon": "Italia", "Old Ship Inn Hackney": "United Kingdom", "Novotel Paris 17": "France", "Hotel Parco di Sch nbrunn Vienna": "\u00d6sterreich", "H tel Thoumieux": "France", "London Marriott Hotel Kensington": "United Kingdom", "Hotel Les Bulles De Paris": "France", "Hotel le Lapin Blanc": "France", "Victoire Germain": "France", "H tel F licien by Elegancia": "France", "La Villa Haussmann": "France", "Hotel Park Villa": "\u00d6sterreich", "Le Pavillon des Lettres": "France", "Hotel The Peninsula Paris": "France", "La Villa Maillot": "France", "Hotel Montaigne": "France", "H tel France d Antin Op ra": "France", "Mokinba Hotels King": "Italia", "London Bridge Hotel": "United Kingdom", "Mercure London Bridge": "United Kingdom", "Hotel Vittoria": "Italia", "Hotel Panache": "France", "Royal Amsterdam Hotel": "Nederland", "Hotel Opera Cadet": "France", "Mercure Paris Montparnasse Raspail": "France", "Exe Vienna": "\u00d6sterreich", "Le Grey Hotel": "France", "Plaza Tour Eiffel": "France", "Relais H tel du Vieux Paris": "France", "Meli Milano": "Italia", "Hotel Plaza Elys es": "France", "Hotel Georgette": "France", "Eurohotel Diagonal Port": "Espanya", "Crowne Plaza Amsterdam South": "Nederland", "AC Hotel Victoria Suites a Marriott Lifestyle Hotel": "Espanya", "Hotel Design Secret de Paris": "France", "Hotel Lombardia": "Italia", "H tel Montmartre Mon Amour": "France", "Hotel Oscar": "France", "11 Cadogan Gardens": "United Kingdom", "Radisson Blu Champs Elys es Paris": "France", "HCC Regente": "Espanya", "Best Western Premier Le Swann": "France", "W Amsterdam": "Nederland", "Tryp Barcelona Condal Mar Hotel": "Espanya", "The Franklin Hotel Starhotels Collezione": "United Kingdom", "H tel De Vend me": "France", "H tel Chaplain Paris Rive Gauche": "France", "Taj 51 Buckingham Gate Suites and Residences": "United Kingdom", "Hotel Spa La Belle Juliette": "France", "R Kipling by Happyculture": "France", "H tel De Buci by MH": "France", "H tel de Lille": "France", "Hotel Pierre Milano": "Italia", "Le Pradey": "France", "Pillows Anna van den Vondel Amsterdam": "Nederland", "Best Western Delphi Hotel": "Nederland", "TownHouse Galleria": "Italia", "Monument Hotel": "Espanya", "Vilana Hotel": "Espa\u00f1a", "H tel Amastan Paris": "France", "Mandarin Oriental Barcelona": "Espanya", "Nolinski Paris": "France", "UNA Hotel Scandinavia": "Italia", "The Berkeley": "United Kingdom", "Shangri La Hotel Paris": "France", "COMO The Halkin": "United Kingdom", "Melia Vienna": "\u00d6sterreich", "Hilton Garden Inn Vienna South": "\u00d6sterreich", "Dorset Square Hotel": "United Kingdom", "Mercure Paris Tour Eiffel Pont Mirabeau": "France", "H tel Le M": "France", "Villa Lut ce Port Royal": "France", "Park Hyatt Milano": "Italia", "Claridge s": "United Kingdom", "Les Plumes Hotel": "France", "Paris Marriott Rive Gauche Hotel": "France", "Room Mate Anna": "Espanya", "Abba Sants": "Espanya", "Morgan Mees": "Nederland", "Sir Adam Hotel": "Nederland", "Hotel Lloyd": "Italia", "Club Hotel Cortina": "\u00d6sterreich", "TownHouse 33": "Italia", "Palazzo Segreti": "Italia", "Ritz Paris": "France", "Hotel Plaza Athenee Paris": "France", "L Empire Paris": "France", "W Paris Op ra": "France", "Vienna Sporthotel": "\u00d6sterreich", "Hotel Montalembert": "France", "Falkensteiner Hotel Wien Margareten": "\u00d6sterreich", "Best Western Hotel Mirage": "Italia", "H tel Vernet": "France", "DoubleTree By Hilton Milan": "Italia", "Maison Borella": "Italia", "Best Western Paris Gare Saint Lazare": "France", "Best Western Hotel Major": "Italia", "Holiday Inn Paris Op ra Grands Boulevards": "France", "Hotel des Tuileries Relais du Silence": "France", "H tel Powers": "France", "Style Hotel": "Italia", "Hotel Raffaello": "Italia", "Avo Hotel": "United Kingdom", "Hotel Mercure Milano Solari": "Italia", "Le Littr ": "France", "Hilton Paris Opera": "France", "H tel Exquis by Elegancia": "France", "Gartenhotel Altmannsdorf Hotel 1": "\u00d6sterreich", "Hotel Sezz Paris": "France", "H tel Le Royal Monceau Raffles Paris": "France", "Hotel Astor Saint Honor ": "France", "Sofitel Paris Le Faubourg": "France", "Pershing Hall": "France", "Le Dokhan s a Tribute Portfolio Hotel": "France", "Hotel Corvinus": "\u00d6sterreich", "InterContinental Amstel Amsterdam": "Nederland", "Hotel Le petit Paris": "France", "Egerton House": "United Kingdom", "H tel Recamier": "France", "Zenit Barcelona": "Espanya", "The LaLit London": "United Kingdom", "Hotel La Lanterne": "France", "Medinaceli": "Espanya", "Simply Rooms Suites": "United Kingdom", "Hotel Gran Derby Suites": "Espanya", "Best Western Mercedes Arc de Triomphe": "France", "Mercure Paris Champs Elys es": "France", "Hilton Barcelona": "Espa\u00f1a", "H tel Bourgogne Montana by MH": "France", "Melia Paris Tour Eiffel": "France", "H tel Pont Royal": "France", "H tel Moli re": "France", "Grand Hotel et de Milan": "Italia", "Renaissance Paris Republique Hotel Spa": "France", "H tel Victor Hugo Paris Kl ber": "France", "Ofelias Hotel 4 Sup": "Espanya", "Balmoral Champs Elys es": "France", "Les Matins de Paris Spa": "France", "H tel Mayfair Paris": "France", "Gran Hotel Barcino": "Espa\u00f1a", "Hotel Boutique Duomo": "Italia", "Melia Paris Vendome": "France", "Amsterdam Canal Residence": "Nederland", "Mercure Milano Regency": "Italia", "Dukes Hotel": "United Kingdom", "Artus Hotel by MH": "France", "H tel Keppler": "France", "Hyatt Regency Amsterdam": "Nederland", "H tel Elysees Mermoz": "France", "Hotel Le 10 BIS": "France", "Hotel du Petit Moulin": "France", "Best Western Allegro Nation": "France", "Hotel Murmuri Barcelona": "Espanya", "H tel Waldorf Trocad ro": "France", "Hotel Tocq": "Italia", "Hotel Mercure Milano Centro": "Italia", "Hotel Imlauer Wien": "\u00d6sterreich", "Hotel Royal Elys es": "France", "Covent Garden Hotel": "United Kingdom", "H tel Juliana Paris": "France", "Mercure Paris Pigalle Sacre Coeur": "France", "Hotel Crivi s": "Italia", "Mercure Paris Opera Grands Boulevards": "France", "Belfast": "France", "H tel Le Relais Saint Germain": "France", "Mokinba Hotels Montebianco": "Italia", "Atala Champs Elys es": "France", "Le 7 Eiffel Hotel": "France", "Lindner Hotel Am Belvedere": "\u00d6sterreich", "H tel Saint Paul Rive Gauche": "France", "H tel Square Louvois": "France", "TH Street Duomo": "Italia", "H tel Jos phine by Happyculture": "France", "Hotel Imperial A Luxury Collection Hotel": "\u00d6sterreich", "Mercure Paris Opera Garnier": "France", "Hotel Mercure La Sorbonne Saint Germain des Pr s": "France", "Franklin Roosevelt": "France", "Le A": "France", "The Level at Melia Barcelona Sky": "Espa\u00f1a", "Le Meurice": "France", "Hotel Rekord": "Espanya", "Hotel Silver": "Italia", "Villa Eugenie": "France", "Hotel Lumen Paris Louvre": "France", "Le Metropolitan a Tribute Portfolio Hotel": "France", "Snob Hotel by Elegancia": "France", "Barcelona Hotel Colonial": "Espanya", "Hotel Dupond Smith": "France", "Splendide Royal Paris": "France", "Hotel Capitol Milano": "Italia", "Hotel Des Saints Peres Esprit de France": "France", "ABaC Restaurant Hotel Barcelona GL Monumento": "Espanya", "Hotel Square": "France", "Mercure Paris Place d Italie": "France", "Monhotel Lounge SPA": "France", "Hotel VIU Milan": "Italia", "Bulgari Hotel Milano": "Italia", "Hotel De Vigny": "France", "The Wellesley Knightsbridge a Luxury Collection Hotel London": "United Kingdom", "The Westin Paris Vend me": "France", "Hotel Verneuil Saint Germain": "France", "Hotel Louvre Montana": "France", "XO Hotel": "France", "Le Roch Hotel Spa": "France", "Hotel Advance": "Espanya", "Mercure Tour Eiffel Grenelle": "France", "Hotel Les Rives de Notre Dame": "France", "Windsor Opera": "France", "Ibis Styles Milano Palmanova": "Italia", "Hotel Stendhal Place Vend me Paris MGallery by Sofitel": "France", "Renaissance Paris Le Parc Trocadero Hotel": "France", "Room Mate Gerard": "Espanya", "Le Lavoisier": "France", "Hotel Villa Lafayette Paris IX": "France", "Mercure Paris 15 Porte de Versailles": "France", "Hotel Le Pera": "France", "H tel Barri re Le Fouquet s": "France", "Renaissance Barcelona Hotel": "Espanya", "Novotel Paris 14 Porte d Orl ans": "France", "BoB Hotel by Elegancia": "France", "Ibis Styles Paris Gare Saint Lazare": "France", "Mercure Paris Bastille Saint Antoine": "France", "Am Spiegeln": "\u00d6sterreich", "Cotton House Hotel Autograph Collection": "Espanya", "Drawing Hotel": "France", "Mercure Paris Gobelins Place d Italie": "France", "Cordial Theaterhotel Wien": "\u00d6sterreich", "Holiday Inn Paris Montparnasse Pasteur": "France", "Hotel Chavanel": "France", "Mercure Paris Porte d Orleans": "France", "Ilunion Bel Art": "Espanya", "Hotel Astra Opera Astotel": "France", "MiHotel": "Italia", "L Edmond H tel": "France", "Victoria Palace Hotel": "France", "The Lanesborough": "United Kingdom", "Hotel Louis 2": "France", "Hotel Eitlj rg": "\u00d6sterreich", "A La Villa Madame": "France", "Hotel Daniel Paris": "France", "Villa Alessandra": "France", "Hotel Whistler": "France", "Boutique H tel Konfidentiel": "France", "Mandarin Oriental Paris": "France", "Hotel Tour d Auvergne Opera": "France", "Duret": "France", "Hotel Wagner": "Italia", "Sansi Pedralbes": "Espanya", "Hotel Eiffel Blomet": "France", "Hotel Le Placide Saint Germain Des Pr s": "France", "AC Hotel Irla a Marriott Lifestyle Hotel": "Espanya", "Kube Hotel Ice Bar": "France", "Hotel Arkadenhof": "\u00d6sterreich", "MARQUIS Faubourg St Honor Relais Ch teaux": "France", "Hotel Seven One Seven": "Nederland", "Hotel Le Saint Gregoire": "France", "Hotel Gallitzinberg": "\u00d6sterreich"}